vcf2ldif/__init__.py
vcf2ldif/__main__.py
vcf2ldif/vcf2ldif.py
vcf2ldif-0.0.6.dist-info/entry_points.txt
vcf2ldif-0.0.6.dist-info/WHEEL
vcf2ldif-0.0.6.dist-info/METADATA
vcf2ldif-0.0.6.dist-info/RECORD
